rtmx/__init__.py
rtmx/__main__.py
rtmx/comparison.py
rtmx/config.py
rtmx/formatting.py
rtmx/graph.py
rtmx/migration.py
rtmx/models.py
rtmx/parser.py
rtmx/py.typed
rtmx/schema.py
rtmx/templates.py
rtmx/validation.py
rtmx/adapters/__init__.py
rtmx/adapters/base.py
rtmx/adapters/github.py
rtmx/adapters/jira.py
rtmx/adapters/mcp/__init__.py
rtmx/adapters/mcp/server.py
rtmx/adapters/mcp/tools.py
rtmx/cli/__init__.py
rtmx/cli/analyze.py
rtmx/cli/backlog.py
rtmx/cli/bootstrap.py
rtmx/cli/config_cmd.py
rtmx/cli/cycles.py
rtmx/cli/deps.py
rtmx/cli/diff.py
rtmx/cli/docs.py
rtmx/cli/from_tests.py
rtmx/cli/git_ops.py
rtmx/cli/health.py
rtmx/cli/init.py
rtmx/cli/install.py
rtmx/cli/integrate.py
rtmx/cli/main.py
rtmx/cli/makefile.py
rtmx/cli/mcp_server.py
rtmx/cli/reconcile.py
rtmx/cli/serve.py
rtmx/cli/setup.py
rtmx/cli/status.py
rtmx/cli/sync.py
rtmx/cli/tui.py
rtmx/extensions/__init__.py
rtmx/pytest/__init__.py
rtmx/pytest/plugin.py
rtmx/web/__init__.py
rtmx/web/app.py
rtmx/web/delta.py
rtmx/web/watcher.py
rtmx/web/routes/__init__.py
rtmx/web/routes/api.py
rtmx/web/routes/pages.py
rtmx/web/routes/websocket.py
rtmx/web/static/styles.css
rtmx/web/templates/backlog.html
rtmx/web/templates/base.html
rtmx/web/templates/dashboard.html
rtmx/web/templates/partials/phase_progress.html
rtmx/web/templates/partials/status_card.html
rtmx-0.0.5.dist-info/METADATA
rtmx-0.0.5.dist-info/WHEEL
rtmx-0.0.5.dist-info/entry_points.txt
rtmx-0.0.5.dist-info/licenses/LICENSE
rtmx-0.0.5.dist-info/licenses/NOTICE
rtmx-0.0.5.dist-info/RECORD
