Metadata-Version: 2.4
Name: rtmx
Version: 0.0.5
Summary: Requirements Traceability Matrix toolkit for GenAI-driven development
Project-URL: Homepage, https://github.com/iotactical/rtmx
Project-URL: Documentation, https://github.com/iotactical/rtmx#readme
Project-URL: Repository, https://github.com/iotactical/rtmx
Project-URL: Issues, https://github.com/iotactical/rtmx/issues
Author-email: ioTACTICAL LLC <engineering@iotactical.co>
License-Expression: Apache-2.0
License-File: LICENSE
License-File: NOTICE
Keywords: cmmc,compliance,fedramp,requirements,rtm,testing,traceability
Classifier: Development Status :: 3 - Alpha
Classifier: Environment :: Console
Classifier: Intended Audience :: Developers
Classifier: License :: OSI Approved :: MIT License
Classifier: Operating System :: OS Independent
Classifier: Programming Language :: Python :: 3
Classifier: Programming Language :: Python :: 3.10
Classifier: Programming Language :: Python :: 3.11
Classifier: Programming Language :: Python :: 3.12
Classifier: Topic :: Software Development :: Quality Assurance
Classifier: Topic :: Software Development :: Testing
Classifier: Typing :: Typed
Requires-Python: >=3.10
Requires-Dist: click>=8.0
Requires-Dist: pandas>=2.0
Requires-Dist: pydantic>=2.0
Requires-Dist: pyyaml>=6.0
Requires-Dist: tabulate>=0.9
Requires-Dist: typing-extensions>=4.0; python_version < '3.11'
Provides-Extra: agents
Requires-Dist: jinja2>=3.0; extra == 'agents'
Provides-Extra: all
Requires-Dist: fastapi>=0.109.0; extra == 'all'
Requires-Dist: jinja2>=3.0; extra == 'all'
Requires-Dist: jira>=3.0; extra == 'all'
Requires-Dist: mcp>=0.1.0; extra == 'all'
Requires-Dist: pygithub>=2.0; extra == 'all'
Requires-Dist: rich>=13.0; extra == 'all'
Requires-Dist: textual>=0.47.0; extra == 'all'
Requires-Dist: uvicorn[standard]>=0.27.0; extra == 'all'
Requires-Dist: watchfiles>=0.21.0; extra == 'all'
Provides-Extra: dev
Requires-Dist: build>=1.0; extra == 'dev'
Requires-Dist: fastapi>=0.109.0; extra == 'dev'
Requires-Dist: httpx>=0.27.0; extra == 'dev'
Requires-Dist: jinja2>=3.0; extra == 'dev'
Requires-Dist: mypy>=1.0; extra == 'dev'
Requires-Dist: pandas-stubs>=2.0; extra == 'dev'
Requires-Dist: pdoc>=14.0; extra == 'dev'
Requires-Dist: pytest-asyncio>=0.23.0; extra == 'dev'
Requires-Dist: pytest-cov>=4.0; extra == 'dev'
Requires-Dist: pytest>=7.0; extra == 'dev'
Requires-Dist: rich>=13.0; extra == 'dev'
Requires-Dist: ruff<0.9.0,>=0.8.0; extra == 'dev'
Requires-Dist: textual>=0.47.0; extra == 'dev'
Requires-Dist: twine>=4.0; extra == 'dev'
Requires-Dist: types-pyyaml>=6.0; extra == 'dev'
Requires-Dist: uvicorn[standard]>=0.27.0; extra == 'dev'
Requires-Dist: watchfiles>=0.21.0; extra == 'dev'
Provides-Extra: github
Requires-Dist: pygithub>=2.0; extra == 'github'
Provides-Extra: jira
Requires-Dist: jira>=3.0; extra == 'jira'
Provides-Extra: mcp
Requires-Dist: mcp>=0.1.0; extra == 'mcp'
Provides-Extra: pytest
Requires-Dist: pytest>=7.0; extra == 'pytest'
Provides-Extra: rich
Requires-Dist: rich>=13.0; extra == 'rich'
Provides-Extra: test-browser
Requires-Dist: playwright>=1.40.0; extra == 'test-browser'
Requires-Dist: pytest-playwright>=0.4.0; extra == 'test-browser'
Provides-Extra: tui
Requires-Dist: textual>=0.47.0; extra == 'tui'
Provides-Extra: web
Requires-Dist: fastapi>=0.109.0; extra == 'web'
Requires-Dist: jinja2>=3.0; extra == 'web'
Requires-Dist: uvicorn[standard]>=0.27.0; extra == 'web'
Requires-Dist: watchfiles>=0.21.0; extra == 'web'
